setup.py
pybuilder_jedi_plugin/__init__.py
pybuilder_jedi_plugin.egg-info/PKG-INFO
pybuilder_jedi_plugin.egg-info/SOURCES.txt
pybuilder_jedi_plugin.egg-info/dependency_links.txt
pybuilder_jedi_plugin.egg-info/entry_points.txt
pybuilder_jedi_plugin.egg-info/requires.txt
pybuilder_jedi_plugin.egg-info/top_level.txt
pybuilder_jedi_plugin.egg-info/zip-safe