Metadata-Version: 1.1
Name: pybuilder-jedi-plugin
Version: 0.0.3
Summary: Lint python sources with the jedi linter (experimental)
Home-page: https://github.com/mriehl/pybuilder_jedi_plugin
Author: Maximilien Riehl
Author-email: max@riehl.io
License: Apache License, Version 2.0
Platform: UNKNOWN
Classifier: Development Status :: 1 - Planning
Classifier: Environment :: Console
Classifier: Intended Audience :: Developers
Classifier: License :: OSI Approved :: Apache Software License
Classifier: Programming Language :: Python
Classifier: Programming Language :: Python :: 2
Classifier: Programming Language :: Python :: 2.7
Classifier: Programming Language :: Python :: 3
Classifier: Programming Language :: Python :: 3.0
Classifier: Programming Language :: Python :: 3.1
Classifier: Programming Language :: Python :: 3.2
Classifier: Programming Language :: Python :: 3.3
Classifier: Topic :: Utilities
